README.md
setup.cfg
setup.py
economypackage/__init__.py
economypackage/mathseconomy/__init__.py
economypackage/mathseconomy/mathsadvancefuncs.py
economypackage/mathseconomy/mymathsUtils.py
pipypackageexample.egg-info/PKG-INFO
pipypackageexample.egg-info/SOURCES.txt
pipypackageexample.egg-info/dependency_links.txt
pipypackageexample.egg-info/top_level.txt