Metadata-Version: 1.0
Name: pipypackageexample
Version: 0.2
Summary: paquete de prueba para una clase udemy
Home-page: https://github.com/aleiarias/pipypackageexample
Author: Alejandra Arias
Author-email: UNKNOWN
License: MIT
Platform: UNKNOWN
